data_reducer/__init__.py
python_data_reducer-0.0.6.dist-info/DESCRIPTION.rst
python_data_reducer-0.0.6.dist-info/METADATA
python_data_reducer-0.0.6.dist-info/RECORD
python_data_reducer-0.0.6.dist-info/WHEEL
python_data_reducer-0.0.6.dist-info/metadata.json
python_data_reducer-0.0.6.dist-info/top_level.txt
