Metadata-Version: 2.0
Name: python-data-reducer
Version: 0.0.6
Summary: This package help you to easily reduce the data input.
Home-page: https://github.com/shinrel22/data_reducer
Author: Tri Nguyen
Author-email: tringuyen5835@gmail.com
License: MIT
Platform: UNKNOWN
Classifier: Intended Audience :: Developers
Classifier: License :: OSI Approved :: MIT License
Classifier: Operating System :: OS Independent
Classifier: Programming Language :: Python
Classifier: Topic :: Software Development :: Libraries :: Python Modules
Requires-Python: >=2.7
